excelToCSV.py
xlsxToCsv-1.0.4.dist-info/LICENSE
xlsxToCsv-1.0.4.dist-info/METADATA
xlsxToCsv-1.0.4.dist-info/WHEEL
xlsxToCsv-1.0.4.dist-info/top_level.txt
xlsxToCsv-1.0.4.dist-info/RECORD
