Metadata-Version: 2.1
Name: xlsxToCsv
Version: 1.0.4
Summary: Takes user specified range data from .xlsx and then converts data to json dict and/or csv.
Home-page: https://github.com/willmichel81/excelToCSV
Author: Will Michel
Author-email: willmichel81@gmail.com
License: UNKNOWN
Project-URL: Bug Tracker, https://github.com/willmichel81/excelToCSV/issues
Keywords: csv,excel,xlsx,excelToCsv,xlsxToCsv
Platform: UNKNOWN
Classifier: Programming Language :: Python :: 3
Classifier: License :: OSI Approved :: MIT License
Classifier: Operating System :: OS Independent
Requires-Python: >=3.6
License-File: LICENSE
